af_runtime_service/__init__.py
af_runtime_service/api_client.py
af_runtime_service/configuration.py
af_runtime_service/rest.py
af_runtime_service/api/__init__.py
af_runtime_service/api/arista_flow_service_api.py
af_runtime_service/api/as_remote_iterator_api.py
af_runtime_service/api/default_api.py
af_runtime_service/api/ns_remote_iterator_api.py
af_runtime_service/api/remote_activity_starting_api.py
af_runtime_service/api/remote_execution_control_manager_api.py
af_runtime_service/api/remote_progress_monitor_api.py
af_runtime_service/api/remote_runtime_environment_api.py
af_runtime_service/api/runtime_service_api.py
af_runtime_service/api/sc_remote_iterator_api.py
af_runtime_service/models/__init__.py
af_runtime_service/models/abort_service_exception.py
af_runtime_service/models/abort_transaction_exception.py
af_runtime_service/models/accessed_process_model_parameter.py
af_runtime_service/models/activity_callback_data.py
af_runtime_service/models/activity_configuration.py
af_runtime_service/models/activity_instance.py
af_runtime_service/models/activity_rest_callback_data.py
af_runtime_service/models/activity_sse_callback_data.py
af_runtime_service/models/activity_state.py
af_runtime_service/models/activity_with_act_state.py
af_runtime_service/models/activity_with_node_state.py
af_runtime_service/models/af_configuration.py
af_runtime_service/models/agent_unknown_exception.py
af_runtime_service/models/as_initial_remote_iterator_data.py
af_runtime_service/models/as_remote_iterator_data.py
af_runtime_service/models/authentication_exception.py
af_runtime_service/models/boolean_reply_message.py
af_runtime_service/models/close_message.py
af_runtime_service/models/commit_message.py
af_runtime_service/models/configuration_exception.py
af_runtime_service/models/data_consistency_exception.py
af_runtime_service/models/data_context.py
af_runtime_service/models/data_source_exception.py
af_runtime_service/models/dummy_parent.py
af_runtime_service/models/ebp_instance_reference.py
af_runtime_service-4.0.3.dist-info/LICENSE
af_runtime_service-4.0.3.dist-info/METADATA
af_runtime_service-4.0.3.dist-info/WHEEL
af_runtime_service-4.0.3.dist-info/top_level.txt
af_runtime_service-4.0.3.dist-info/RECORD
