Metadata-Version: 2.1
Name: af-runtime-service
Version: 4.0.3
Summary: AristaFlow BPM RuntimeService/RuntimeService REST Client
Home-page: UNKNOWN
Author: AristaFlow GmbH
Author-email: info@aristaflow.com
License: UNKNOWN
Keywords: Swagger,AristaFlowREST/RuntimeService
Platform: UNKNOWN
Requires-Dist: certifi
Requires-Dist: python-dateutil
Requires-Dist: six (>=1.10)
Requires-Dist: urllib3 (>=1.15)
